setup.py
binwalk/__init__.py
binwalk.egg-info/PKG-INFO
binwalk.egg-info/SOURCES.txt
binwalk.egg-info/dependency_links.txt
binwalk.egg-info/top_level.txt
scripts/binwalk