Metadata-Version: 1.0
Name: binwalk
Version: 2.1.0
Summary: Firmware analysis tool
Home-page: https://github.com/devttys0/binwalk
Author: Craig Heffner
Author-email: UNKNOWN
License: UNKNOWN
Platform: UNKNOWN
